pep621.py
pep621-0.4.0.post2.dist-info/LICENSE
pep621-0.4.0.post2.dist-info/METADATA
pep621-0.4.0.post2.dist-info/WHEEL
pep621-0.4.0.post2.dist-info/top_level.txt
pep621-0.4.0.post2.dist-info/RECORD
