Metadata-Version: 2.1
Name: pep621
Version: 0.4.0.post2
Summary: PEP 621 metadata parsing
Author: Filipe Laíns
Author-email: lains@riseup.net
License: MIT
Project-URL: homepage, https://github.com/FFY00/python-pep621
Project-URL: changelog, https://pep621.readthedocs.io/en/stable/changelog.html
Classifier: License :: OSI Approved :: MIT License
Classifier: Programming Language :: Python :: 3
Classifier: Programming Language :: Python :: 3 :: Only
Classifier: Programming Language :: Python :: 3.7
Classifier: Programming Language :: Python :: 3.8
Classifier: Programming Language :: Python :: 3.9
Requires-Python: >=3.7
License-File: LICENSE
Requires-Dist: packaging (>=19.0)
Provides-Extra: docs
Requires-Dist: furo (>=2020.11.19b18) ; extra == 'docs'
Requires-Dist: sphinx (~=3.0) ; extra == 'docs'
Requires-Dist: sphinx-autodoc-typehints (>=1.10.0) ; extra == 'docs'
Provides-Extra: test
Requires-Dist: pytest (>=6.2.4) ; extra == 'test'
Requires-Dist: pytest-cov (>=2) ; extra == 'test'
Requires-Dist: tomli (>=1.0.0) ; extra == 'test'
